odoo/addons/project_task_code_portal/README.rst
odoo/addons/project_task_code_portal/__init__.py
odoo/addons/project_task_code_portal/__manifest__.py
odoo/addons/project_task_code_portal/controllers/__init__.py
odoo/addons/project_task_code_portal/controllers/portal.py
odoo/addons/project_task_code_portal/i18n/it.po
odoo/addons/project_task_code_portal/i18n/project_task_code_portal.pot
odoo/addons/project_task_code_portal/models/__init__.py
odoo/addons/project_task_code_portal/models/project_task.py
odoo/addons/project_task_code_portal/readme/CONFIGURE.md
odoo/addons/project_task_code_portal/readme/CONTEXT.md
odoo/addons/project_task_code_portal/readme/CONTRIBUTORS.md
odoo/addons/project_task_code_portal/readme/DESCRIPTION.md
odoo/addons/project_task_code_portal/readme/HISTORY.md
odoo/addons/project_task_code_portal/readme/USAGE.md
odoo/addons/project_task_code_portal/readme/newsfragments/.gitkeep
odoo/addons/project_task_code_portal/static/description/icon.png
odoo/addons/project_task_code_portal/static/description/index.html
odoo/addons/project_task_code_portal/templates/portal_templates.xml
odoo/addons/project_task_code_portal/tests/__init__.py
odoo/addons/project_task_code_portal/tests/test_portal.py
odoo_addon_project_task_code_portal-16.0.1.1.0.dist-info/METADATA
odoo_addon_project_task_code_portal-16.0.1.1.0.dist-info/WHEEL
odoo_addon_project_task_code_portal-16.0.1.1.0.dist-info/top_level.txt
odoo_addon_project_task_code_portal-16.0.1.1.0.dist-info/RECORD
