Metadata-Version: 2.1
Name: odoo-addon-project_task_code_portal
Version: 16.0.1.1.0
Summary: Use custom task code in customer portal
Home-page: https://github.com/OCA/project
Author: Cetmix OÜ, Odoo Community Association (OCA)
Author-email: support@odoo-community.org
License: AGPL-3
Classifier: Programming Language :: Python
Classifier: Framework :: Odoo
Classifier: Framework :: Odoo :: 16.0
Classifier: License :: OSI Approved :: GNU Affero General Public License v3
Classifier: Development Status :: 4 - Beta
Requires-Python: >=3.10
Requires-Dist: odoo-addon-project-task-code<16.1dev,>=16.0dev
Requires-Dist: odoo<16.1dev,>=16.0a
